osqur/__init__.py
osqur-0.1.0.dist-info/LICENSE
osqur-0.1.0.dist-info/METADATA
osqur-0.1.0.dist-info/WHEEL
osqur-0.1.0.dist-info/RECORD
