Metadata-Version: 2.1
Name: osqur
Version: 0.1.0
Summary: Quantitative UX Research in Python
License: MIT
Author: Mason Sun
Author-email: masonzsun@gmail.com
Requires-Python: >=3.9,<4.0
Classifier: License :: OSI Approved :: MIT License
Classifier: Programming Language :: Python :: 3
Classifier: Programming Language :: Python :: 3.9
Classifier: Programming Language :: Python :: 3.10
Classifier: Programming Language :: Python :: 3.11
Requires-Dist: notebook (>=7.0.3,<8.0.0)
Requires-Dist: pandas (>=2.0.3,<3.0.0)
